ntlm_info/__init__.py
ntlm_info/challenge_parser.py
ntlm_info/main.py
ntlm_info/requester.py
ntlm_info-0.0.1.dist-info/LICENSE
ntlm_info-0.0.1.dist-info/METADATA
ntlm_info-0.0.1.dist-info/WHEEL
ntlm_info-0.0.1.dist-info/entry_points.txt
ntlm_info-0.0.1.dist-info/top_level.txt
ntlm_info-0.0.1.dist-info/RECORD
