Metadata-Version: 2.1
Name: ntlm-info
Version: 0.0.1
Summary: Get system info from NTLM
Home-page: UNKNOWN
Author: Eloy Perez
Author-email: zer1t0ps@protonmail.com
License: UNKNOWN
Platform: UNKNOWN
Classifier: Programming Language :: Python :: 3
Classifier: License :: OSI Approved :: GNU General Public License v3 (GPLv3)
Requires-Dist: impacket
Requires-Dist: requests
